geoindex_rs-0.2.1.dist-info/METADATA
geoindex_rs-0.2.1.dist-info/WHEEL
geoindex_rs/__init__.py
geoindex_rs/_rust.cpython-310-powerpc64le-linux-gnu.so
geoindex_rs/_rust.pyi
geoindex_rs/enums.py
geoindex_rs/kdtree.pyi
geoindex_rs/py.typed
geoindex_rs/rtree.pyi
geoindex_rs-0.2.1.dist-info/RECORD
