Metadata-Version: 2.4
Name: geoindex-rs
Version: 0.2.1
Classifier: Programming Language :: Rust
Classifier: Programming Language :: Python :: Implementation :: CPython
Classifier: Programming Language :: Python :: Implementation :: PyPy
Requires-Dist: arro3-core
Requires-Python: >=3.9
